chanda/__init__.py
chanda/cli.py
chanda/core.py
chanda/exceptions.py
chanda/utils.py
chanda/data/chanda_ardhasama.csv
chanda/data/chanda_jaati.csv
chanda/data/chanda_matra.csv
chanda/data/chanda_sama.csv
chanda/data/chanda_vishama.csv
chanda/data/examples.json
chanda-0.1.1.dist-info/licenses/LICENSE
chanda-0.1.1.dist-info/METADATA
chanda-0.1.1.dist-info/WHEEL
chanda-0.1.1.dist-info/entry_points.txt
chanda-0.1.1.dist-info/top_level.txt
chanda-0.1.1.dist-info/RECORD
