Metadata-Version: 2.4
Name: chanda
Version: 0.1.1
Summary: Sanskrit meter identification and analysis library
Home-page: https://github.com/hrishikeshrt/chanda
Author: Hrishikesh Terdalkar
Author-email: Hrishikesh Terdalkar <hrishikeshrt@proton.me>
License: AGPL-3.0-or-later
Project-URL: Homepage, https://github.com/hrishikeshrt/chanda
Project-URL: Documentation, https://chanda.readthedocs.io
Project-URL: Repository, https://github.com/hrishikeshrt/chanda
Project-URL: Bug Tracker, https://github.com/hrishikeshrt/chanda/issues
Keywords: sanskrit,prosody,meter,chanda,poetry,linguistics,nlp,digital-humanities
Classifier: Development Status :: 3 - Alpha
Classifier: Intended Audience :: Developers
Classifier: Intended Audience :: Education
Classifier: Intended Audience :: Science/Research
Classifier: License :: OSI Approved :: GNU Affero General Public License v3 or later (AGPLv3+)
Classifier: Programming Language :: Python :: 3
Classifier: Programming Language :: Python :: 3.7
Classifier: Programming Language :: Python :: 3.8
Classifier: Programming Language :: Python :: 3.9
Classifier: Programming Language :: Python :: 3.10
Classifier: Programming Language :: Python :: 3.11
Classifier: Programming Language :: Python :: 3.12
Classifier: Topic :: Text Processing :: Linguistic
Classifier: Topic :: Software Development :: Libraries :: Python Modules
Requires-Python: >=3.8
License-File: LICENSE
Requires-Dist: python-Levenshtein>=0.12.2
Requires-Dist: indic-transliteration>=2.3.10
Requires-Dist: sanskrit-text>=0.2.1
Provides-Extra: dev
Requires-Dist: pytest>=7.0; extra == "dev"
Requires-Dist: pytest-cov>=3.0; extra == "dev"
Requires-Dist: black>=22.0; extra == "dev"
Requires-Dist: flake8>=4.0; extra == "dev"
Requires-Dist: mypy>=0.950; extra == "dev"
Provides-Extra: docs
Requires-Dist: sphinx>=4.0; extra == "docs"
Requires-Dist: sphinx-rtd-theme>=1.0; extra == "docs"
Requires-Dist: sphinx-autodoc-typehints>=1.18; extra == "docs"
Provides-Extra: webapp
Requires-Dist: Flask>=2.2.2; extra == "webapp"
Requires-Dist: Flask-Uploads>=0.2.1; extra == "webapp"
Requires-Dist: pytesseract>=0.3.9; extra == "webapp"
Requires-Dist: google-drive-ocr>=0.2.6; extra == "webapp"
Dynamic: author
Dynamic: home-page
Dynamic: license-file
Dynamic: requires-python
